splunkautomator/__init__.py
splunkautomator/SplunkAutomator.py
splunkautomator-0.1.3.dist-info/WHEEL
splunkautomator-0.1.3.dist-info/METADATA
splunkautomator-0.1.3.dist-info/RECORD
