Metadata-Version: 2.1
Name: splunkautomator
Version: 0.1.3
Summary: 
Author: PeterWeiderer
Author-email: peter.weiderer@bmw.de
Requires-Python: >=3.8,<4.0
Classifier: Programming Language :: Python :: 3
Classifier: Programming Language :: Python :: 3.10
Classifier: Programming Language :: Python :: 3.8
Classifier: Programming Language :: Python :: 3.9
Requires-Dist: requests (>=2.13.0,<3.0.0)
